adhoccomputing/GenericModel.py
adhoccomputing/Generics.py
adhoccomputing/__init__.py
adhoccomputing/DistributedAlgorithms/__init__.py
adhoccomputing/DistributedAlgorithms/AnonymousNetworks/IEEE1394.py
adhoccomputing/DistributedAlgorithms/AnonymousNetworks/ItaiRodeh.py
adhoccomputing/DistributedAlgorithms/AnonymousNetworks/__init__.py
adhoccomputing/DistributedAlgorithms/Broadcasting/Broadcasting.py
adhoccomputing/DistributedAlgorithms/Broadcasting/__init__.py
adhoccomputing/DistributedAlgorithms/Clocks/LogicalClocks.py
adhoccomputing/DistributedAlgorithms/Clocks/__init__.py
adhoccomputing/DistributedAlgorithms/Election/EchoExtinction.py
adhoccomputing/DistributedAlgorithms/Election/Spira.py
adhoccomputing/DistributedAlgorithms/Election/__init__.py
adhoccomputing/DistributedAlgorithms/FailureDetectors/FailureDetectors.py
adhoccomputing/DistributedAlgorithms/FailureDetectors/__init__.py
adhoccomputing/DistributedAlgorithms/MutualExclusion/Raymond.py
adhoccomputing/DistributedAlgorithms/MutualExclusion/RicartAgrawala.py
adhoccomputing/DistributedAlgorithms/MutualExclusion/__init__.py
adhoccomputing/DistributedAlgorithms/Snapshot/Snapshot.py
adhoccomputing/DistributedAlgorithms/Snapshot/__init__.py
adhoccomputing/DistributedAlgorithms/Waves/AwerbuchDFS.py
adhoccomputing/DistributedAlgorithms/Waves/CidonDFS.py
adhoccomputing/DistributedAlgorithms/Waves/DepthFirstSearch.py
adhoccomputing/DistributedAlgorithms/Waves/Tarrys.py
adhoccomputing/DistributedAlgorithms/Waves/TreeAlgorithm.py
adhoccomputing/DistributedAlgorithms/Waves/__init__.py
adhoccomputing/Distribution/AHCManager.py
adhoccomputing/Distribution/LogicalChannelProcess.py
adhoccomputing/Distribution/NodeProcess.py
adhoccomputing/Distribution/__init__.py
adhoccomputing/Experimentation/Experiment.py
adhoccomputing/Experimentation/Parser.py
adhoccomputing/Experimentation/Topology.py
adhoccomputing/Experimentation/__init__.py
adhoccomputing/Networking/OSIModel.py
adhoccomputing/Networking/__init__.py
adhoccomputing-2.1.7.dist-info/LICENSE
adhoccomputing-2.1.7.dist-info/METADATA
adhoccomputing-2.1.7.dist-info/WHEEL
adhoccomputing-2.1.7.dist-info/top_level.txt
adhoccomputing-2.1.7.dist-info/RECORD
