Metadata-Version: 2.1
Name: adhoccomputing
Version: 2.1.7
Summary: Ad Hoc Computing Library
Home-page: https://github.com/cengwins/ahc
Author: CengWins
Author-email: ahc@ceng.metu.edu.tr
License: GPL V3
Project-URL: Bug Tracker, https://github.com/cengwins/ahc/issues
Project-URL: Simulator Website, https://ahc.ceng.metu.edu.tr
Classifier: Programming Language :: Python :: 3
Classifier: Operating System :: OS Independent
Requires-Python: >=3.8
License-File: LICENSE
